{
  "generator-jhipster": {
    "promptValues": {
      "packageName": "com.customeranalytics",
      "nativeLanguage": "en"
    },
    "jhipsterVersion": "4.13.0",
    "baseName": "customeranalytics",
    "packageName": "com.customeranalytics",
    "packageFolder": "com/customeranalytics",
    "serverPort": "8095",
    "authenticationType": "jwt",
    "hibernateCache": "hazelcast",
    "clusteredHttpSession": false,
    "websocket": "spring-websocket",
    "databaseType": "sql",
    "devDatabaseType": "postgresql",
    "prodDatabaseType": "postgresql",
    "searchEngine": false,
    "messageBroker": false,
    "serviceDiscoveryType": "eureka",
    "buildTool": "maven",
    "enableSocialSignIn": false,
    "enableSwaggerCodegen": false,
    "jwtSecretKey": "2aaa0c2687c6a0c0f6fded87d64ff18c89e680d7",
    "clientFramework": "angular1",
    "useSass": false,
    "clientPackageManager": "yarn",
    "applicationType": "gateway",
    "testFrameworks": [
      "gatling",
      "cucumber",
      "protractor"
    ],
    "jhiPrefix": "jhi",
    "enableTranslation": true,
    "nativeLanguage": "en",
    "languages": [
      "en",
      "tr"
    ]
  }
}